README.md
setup.py
indb/__init__.py
indb/clients.py
indb/utils.py
indb.egg-info/PKG-INFO
indb.egg-info/SOURCES.txt
indb.egg-info/dependency_links.txt
indb.egg-info/not-zip-safe
indb.egg-info/requires.txt
indb.egg-info/top_level.txt
indb/schemata/__init__.py
indb/schemata/infinity.py
indb/schemata/wikidata.py