Metadata-Version: 2.1
Name: indb
Version: 0.0.5
Summary: Infinity database.
Home-page: https://github.com/infamily/indb
Author: Mindey
Author-email: mindey@qq.com
License: AGPL
Platform: UNKNOWN
Provides-Extra: test
